smm_utils/__init__.py
smm_utils-0.0.3.dist-info/LICENSE
smm_utils-0.0.3.dist-info/METADATA
smm_utils-0.0.3.dist-info/WHEEL
smm_utils-0.0.3.dist-info/top_level.txt
smm_utils-0.0.3.dist-info/RECORD
