Metadata-Version: 2.1
Name: smm-utils
Version: 0.0.3
Summary: Utilities for smm guru project
Home-page: https://gitlab.com/smm-guru/smm-utils
Author: Evgeny Basmov
Author-email: coykto@gmail.com
License: MIT
Platform: OS Independent
Classifier: Development Status :: 3 - Alpha
Classifier: Framework :: Django :: 1.8
Classifier: Framework :: Django :: 1.9
Classifier: Environment :: Web Environment
Classifier: Operating System :: OS Independent
Classifier: Programming Language :: Python :: 2.7
Classifier: Programming Language :: Python :: 3.5
Classifier: Intended Audience :: Developers
Classifier: License :: OSI Approved :: MIT License
